FileToFolder/__init__.py
FileToFolder/main.py
file_to_folder-0.0.0.1.dist-info/LICENSE.txt
file_to_folder-0.0.0.1.dist-info/METADATA
file_to_folder-0.0.0.1.dist-info/WHEEL
file_to_folder-0.0.0.1.dist-info/top_level.txt
file_to_folder-0.0.0.1.dist-info/RECORD
