Metadata-Version: 2.1
Name: file-to-folder
Version: 0.0.0.1
Summary: My short description for my project.
Home-page: https://github.com/me/myproject
Author: Star0ZeroE
Author-email: star0zeroe@qq.com
License: MIT
Classifier: License :: OSI Approved :: MIT License
Classifier: Programming Language :: Python
Classifier: Programming Language :: Python :: 3
Classifier: Programming Language :: Python :: 3.6
Classifier: Programming Language :: Python :: Implementation :: CPython
Classifier: Programming Language :: Python :: Implementation :: PyPy
Requires-Python: >=3.6.0
License-File: LICENSE.txt
